Metadata-Version: 2.1
Name: balala-mongoengine
Version: 0.0.3
Summary: a copy of MongoEngineMongoEngine is a Python Object-Document Mapper for working with MongoDB.
Home-page: http://mongoengine.org/
Author: Harry Marr
Author-email: harry.marr@gmail.com
Maintainer: Stefan Wojcik
Maintainer-email: wojcikstefan@gmail.com
License: MIT
Download-URL: https://github.com/MongoEngine/mongoengine/tarball/master
Platform: any
Classifier: Development Status :: 4 - Beta
Classifier: Intended Audience :: Developers
Classifier: License :: OSI Approved :: MIT License
Classifier: Operating System :: OS Independent
Classifier: Programming Language :: Python
Classifier: Programming Language :: Python :: 3.5
Classifier: Programming Language :: Python :: 3.6
Classifier: Programming Language :: Python :: Implementation :: CPython
Classifier: Programming Language :: Python :: Implementation :: PyPy
Classifier: Topic :: Database
Classifier: Topic :: Software Development :: Libraries :: Python Modules
Requires-Dist: pymongo (>=3.8)
Requires-Dist: six
